setup.py
hisp/__init__.py
hisp/doctypes.py
hisp/exceptions.py
hisp/macros.py
hisp/nodes.py
hisp/parse.py
hisp/tokenize.py
hisp.egg-info/PKG-INFO
hisp.egg-info/SOURCES.txt
hisp.egg-info/dependency_links.txt
hisp.egg-info/requires.txt
hisp.egg-info/top_level.txt
hisp/libraries/__init__.py
hisp/libraries/core.py
hisp/libraries/django.py
hisp/loaders/__init__.py
hisp/loaders/compiled.py
hisp/loaders/convert.py
hisp/management/__init__.py
hisp/management/commands/__init__.py
hisp/management/commands/hisp_clean.py
hisp/management/commands/hisp_convert.py
hisp/tables/__init__.py
hisp/tables/lextab.py
hisp/tables/parsetab.py