Metadata-Version: 1.0
Name: hisp
Version: 0.1.0
Summary: HTML Generator. Lisp syntax. Django integration.
Home-page: UNKNOWN
Author: Nate Soares
Author-email: nate@natesoares.com
License: MIT
Platform: UNKNOWN
